yourbench/__init__.py
yourbench/__main__.py
yourbench/main.py
yourbench/conf/__init__.py
yourbench/conf/loader.py
yourbench/conf/prompts.py
yourbench/conf/schema.py
yourbench/pipeline/__init__.py
yourbench/pipeline/chunking.py
yourbench/pipeline/citation_score_filtering.py
yourbench/pipeline/handler.py
yourbench/pipeline/ingestion.py
yourbench/pipeline/prepare_lighteval.py
yourbench/pipeline/question_rewriting.py
yourbench/pipeline/summarization.py
yourbench/pipeline/question_generation/__init__.py
yourbench/pipeline/question_generation/_core.py
yourbench/pipeline/question_generation/cross_document.py
yourbench/pipeline/question_generation/multi_hop.py
yourbench/pipeline/question_generation/single_hop.py
yourbench/prompts/README.md
yourbench/prompts/ingestion/pdf_llm_prompt.md
yourbench/prompts/qa/gold_qa_user_prompt.md
yourbench/prompts/qa/judge_answer_system_prompt.md
yourbench/prompts/qa/judge_answer_user_prompt.md
yourbench/prompts/qa/zeroshot_qa_user_prompt.md
yourbench/prompts/question_generation/multi_hop_system_prompt.md
yourbench/prompts/question_generation/multi_hop_system_prompt_multi.md
yourbench/prompts/question_generation/multi_hop_user_prompt.md
yourbench/prompts/question_generation/single_hop_system_prompt.md
yourbench/prompts/question_generation/single_hop_system_prompt_multi.md
yourbench/prompts/question_generation/single_hop_user_prompt.md
yourbench/prompts/question_rewriting/question_rewriting_system_prompt.md
yourbench/prompts/question_rewriting/question_rewriting_user_prompt.md
yourbench/prompts/summarization/combine_summaries_user_prompt.md
yourbench/prompts/summarization/summarization_user_prompt.md
yourbench/utils/__init__.py
yourbench/utils/chunking_utils.py
yourbench/utils/cross_document_utils.py
yourbench/utils/dataset_card.py
yourbench/utils/dataset_engine.py
yourbench/utils/env.py
yourbench/utils/logging_context.py
yourbench/utils/parsing_engine.py
yourbench/utils/prompt_builder.py
yourbench/utils/question_models.py
yourbench-0.9.0.dist-info/licenses/LICENSE
yourbench-0.9.0.dist-info/METADATA
yourbench-0.9.0.dist-info/WHEEL
yourbench-0.9.0.dist-info/entry_points.txt
yourbench-0.9.0.dist-info/top_level.txt
yourbench-0.9.0.dist-info/RECORD
