Metadata-Version: 2.4
Name: yourbench
Version: 0.9.0
Summary: Dynamic Evaluation Set Generation with Large Language Models
Author-email: Sumuk Shashidhar <sumuks2@illinois.edu>, Alina Lozovskaia <alina.lozovskaia@huggingface.co>, Clémentine Fourrier <clementine@huggingface.co>, Nathan Habib <nathan.habib@huggingface.co>
Requires-Python: <3.13,>=3.12
License-File: LICENSE
Requires-Dist: asyncio>=3.4.3
Requires-Dist: click>=8.1.7
Requires-Dist: datasets>=3.3.0
Requires-Dist: hf-transfer>=0.1.9
Requires-Dist: huggingface-hub[hf_xet,inference]>=0.34.3
Requires-Dist: hydra-core>=1.3.2
Requires-Dist: jinja2>=3.1.6
Requires-Dist: loguru>=0.7.3
Requires-Dist: markitdown[all]>=0.0.2
Requires-Dist: numpy>=1.24.0
Requires-Dist: omegaconf>=2.3.0
Requires-Dist: pillow>=11.2.1
Requires-Dist: pydantic>=2.11.7
Requires-Dist: pymupdf>=1.26.1
Requires-Dist: python-dotenv>=1.0.1
Requires-Dist: pyyaml>=6.0.0
Requires-Dist: randomname>=0.2.1
Requires-Dist: rich>=13.7.0
Requires-Dist: ruff>=0.11.1
Requires-Dist: thefuzz>=0.22.1
Requires-Dist: tiktoken>=0.9.0
Requires-Dist: tqdm>=4.67.1
Requires-Dist: trafilatura>=2.0.0
Requires-Dist: typer>=0.15.2
Provides-Extra: llm
Requires-Dist: markitdown[all]>=0.0.2; extra == "llm"
Dynamic: license-file
